fritzconnection/__init__.py
fritzconnection/cli/__init__.py
fritzconnection/cli/fritzcall.py
fritzconnection/cli/fritzhomeauto.py
fritzconnection/cli/fritzhosts.py
fritzconnection/cli/fritzinspection.py
fritzconnection/cli/fritzmonitor.py
fritzconnection/cli/fritzphonebook.py
fritzconnection/cli/fritzstatus.py
fritzconnection/cli/fritzwlan.py
fritzconnection/cli/utils.py
fritzconnection/core/__init__.py
fritzconnection/core/devices.py
fritzconnection/core/exceptions.py
fritzconnection/core/fritzconnection.py
fritzconnection/core/fritzhttp.py
fritzconnection/core/fritzmonitor.py
fritzconnection/core/logger.py
fritzconnection/core/processor.py
fritzconnection/core/soaper.py
fritzconnection/core/utils.py
fritzconnection/lib/__init__.py
fritzconnection/lib/fritzbase.py
fritzconnection/lib/fritzcall.py
fritzconnection/lib/fritzhomeauto.py
fritzconnection/lib/fritzhosts.py
fritzconnection/lib/fritzphonebook.py
fritzconnection/lib/fritzstatus.py
fritzconnection/lib/fritztools.py
fritzconnection/lib/fritztopology.py
fritzconnection/lib/fritzwlan.py
fritzconnection-1.15.1.dist-info/licenses/LICENSE.txt
fritzconnection-1.15.1.dist-info/METADATA
fritzconnection-1.15.1.dist-info/WHEEL
fritzconnection-1.15.1.dist-info/entry_points.txt
fritzconnection-1.15.1.dist-info/top_level.txt
fritzconnection-1.15.1.dist-info/RECORD
