Metadata-Version: 2.4
Name: fritzconnection
Version: 1.15.1
Summary: Communicate with the AVM FRITZ!Box
Home-page: https://github.com/kbr/fritzconnection
Author: Klaus Bremer
Author-email: bremer@bremer-media.com
License: MIT
Keywords: AVM FRITZ!Box fritzbox fritz TR-064 AHA-HTTP homeautomation
Classifier: Development Status :: 5 - Production/Stable
Classifier: Environment :: Console
Classifier: Intended Audience :: Developers
Classifier: License :: OSI Approved :: MIT License
Classifier: Natural Language :: English
Classifier: Operating System :: OS Independent
Classifier: Programming Language :: Python :: 3
Classifier: Programming Language :: Python :: 3.7
Classifier: Programming Language :: Python :: 3.8
Classifier: Programming Language :: Python :: 3.9
Classifier: Programming Language :: Python :: 3.10
Classifier: Programming Language :: Python :: 3.11
Classifier: Programming Language :: Python :: 3.12
Classifier: Programming Language :: Python :: 3.13
Classifier: Programming Language :: Python :: 3.14
Classifier: Topic :: Software Development :: Libraries :: Python Modules
Requires-Python: >= 3.7
License-File: LICENSE.txt
Requires-Dist: requests>=2.22.0
Provides-Extra: qr
Requires-Dist: segno>=1.4.1; extra == "qr"
Dynamic: author
Dynamic: author-email
Dynamic: classifier
Dynamic: description
Dynamic: description-content-type
Dynamic: home-page
Dynamic: keywords
Dynamic: license
Dynamic: license-file
Dynamic: provides-extra
Dynamic: requires-dist
Dynamic: requires-python
Dynamic: summary
